CHANGELOG.txt
LICENSE.txt
MANIFEST.in
README.md
setup.py
Generation_Image_Gaston/__init__.py
Generation_Image_Gaston.egg-info/PKG-INFO
Generation_Image_Gaston.egg-info/SOURCES.txt
Generation_Image_Gaston.egg-info/dependency_links.txt
Generation_Image_Gaston.egg-info/requires.txt
Generation_Image_Gaston.egg-info/top_level.txt