Metadata-Version: 2.1
Name: Generation-Image-Gaston
Version: 0.2.2
Author: Gaston Robé
Author-email: gaston01.robe@gmail.com
License: MIT
Keywords: Capitain America Avengers
Classifier: Development Status :: 5 - Production/Stable
Classifier: Intended Audience :: Education
Classifier: Operating System :: Microsoft :: Windows :: Windows 11
Classifier: License :: OSI Approved :: MIT License
Classifier: Programming Language :: Python :: 3
License-File: LICENSE.txt
